adafmt/LICENSE
adafmt/__init__.py
adafmt/__main__.py
adafmt/als_client.py
adafmt/als_initializer.py
adafmt/argument_validator.py
adafmt/cleanup_handler.py
adafmt/cli.py
adafmt/cli_helpers.py
adafmt/default_paths.py
adafmt/edits.py
adafmt/error_writer.py
adafmt/file_discovery.py
adafmt/file_discovery_new.py
adafmt/file_processor.py
adafmt/final_reporter.py
adafmt/initializer.py
adafmt/logging_jsonl.py
adafmt/logging_setup.py
adafmt/metrics.py
adafmt/metrics_reporter.py
adafmt/path_validator.py
adafmt/pattern_formatter.py
adafmt/pattern_loader.py
adafmt/pattern_validator.py
adafmt/run_setup.py
adafmt/stderr_handler.py
adafmt/tui.py
adafmt/utils.py
adafmt-1.0.0.dist-info/licenses/LICENSE
adafmt-1.0.0.dist-info/METADATA
adafmt-1.0.0.dist-info/WHEEL
adafmt-1.0.0.dist-info/entry_points.txt
adafmt-1.0.0.dist-info/top_level.txt
adafmt-1.0.0.dist-info/RECORD
