Metadata-Version: 2.4
Name: adafmt
Version: 1.0.0
Summary: Ada Language Formatter (ALS-backed, Customizable)
Author: Michael Gardner, A Bit of Help, Inc.
License: BSD-3-Clause
Project-URL: Homepage, https://github.com/abitofhelp/adafmt
Project-URL: Source, https://github.com/abitofhelp/adafmt
Project-URL: Changelog, https://github.com/abitofhelp/adafmt/releases
Project-URL: Issues, https://github.com/abitofhelp/adafmt/issues
Keywords: ada,formatter,lsp,als,cli
Classifier: License :: OSI Approved :: BSD License
Classifier: Programming Language :: Python :: 3
Classifier: Programming Language :: Python :: 3 :: Only
Classifier: Programming Language :: Python :: 3.11
Classifier: Programming Language :: Python :: 3.12
Requires-Python: >=3.11
License-File: LICENSE
Requires-Dist: typer>=0.9.0
Requires-Dist: tabulate>=0.9.0
Provides-Extra: dev
Requires-Dist: pytest>=7.0; extra == "dev"
Requires-Dist: pytest-cov; extra == "dev"
Requires-Dist: pytest-asyncio; extra == "dev"
Requires-Dist: black; extra == "dev"
Requires-Dist: mypy; extra == "dev"
Requires-Dist: ruff; extra == "dev"
Provides-Extra: test
Requires-Dist: pytest>=7.0; extra == "test"
Requires-Dist: pytest-asyncio; extra == "test"
Provides-Extra: patterns
Requires-Dist: regex>=2022.0.0; extra == "patterns"
Dynamic: license-file
